bwapi/__init__.py
bwapi/authenticate.py
bwapi/bwdata.py
bwapi/bwproject.py
bwapi/bwresources.py
bwapi/credentials.py
bwapi/filters.py
bwapi-4.1.0.dist-info/LICENSE.md
bwapi-4.1.0.dist-info/METADATA
bwapi-4.1.0.dist-info/WHEEL
bwapi-4.1.0.dist-info/entry_points.txt
bwapi-4.1.0.dist-info/top_level.txt
bwapi-4.1.0.dist-info/RECORD
