Metadata-Version: 2.1
Name: bwapi
Version: 4.1.0
Summary: A software development kit for the Brandwatch API
Home-page: https://github.com/BrandwatchLtd/api_sdk
Author: Amy Barker, Jamie Lebovics, Paul Siegel and Jessica Bowden
Author-email: amyb@brandwatch.com, paul@brandwatch.com, jess@brandwatch.com
License: License :: OSI Approved :: MIT License
Platform: UNKNOWN
Classifier: Development Status :: 5 - Production/Stable
Classifier: Intended Audience :: Developers
Classifier: License :: OSI Approved :: MIT License
Classifier: Programming Language :: Python :: 3
Classifier: Programming Language :: Python :: 3.5
Classifier: Programming Language :: Python :: 3.6
Classifier: Programming Language :: Python :: 3.7
Classifier: Programming Language :: Python :: 3.8
Requires-Python: >=3.5
Requires-Dist: requests (>=2.22.0)
